hynet/__init__.py
hynet/__main__.py
hynet/config.py
hynet/types_.py
hynet/data/__init__.py
hynet/data/connection.py
hynet/data/example_days.py
hynet/data/import_.py
hynet/data/interface.py
hynet/data/structure.py
hynet/distributed/__init__.py
hynet/distributed/client.py
hynet/distributed/server.py
hynet/model/__init__.py
hynet/model/steady_state.py
hynet/opf/__init__.py
hynet/opf/calc.py
hynet/opf/result.py
hynet/qcqp/__init__.py
hynet/qcqp/problem.py
hynet/qcqp/result.py
hynet/qcqp/solver.py
hynet/reduction/__init__.py
hynet/reduction/copper_plate.py
hynet/scenario/__init__.py
hynet/scenario/capability.py
hynet/scenario/cost.py
hynet/scenario/representation.py
hynet/scenario/verification.py
hynet/solver/__init__.py
hynet/solver/cvxpy.py
hynet/solver/ipopt.py
hynet/solver/mosek.py
hynet/solver/picos.py
hynet/solver/pyomo.py
hynet/test/__init__.py
hynet/test/installation.py
hynet/test/regression.py
hynet/test/system.py
hynet/utilities/__init__.py
hynet/utilities/base.py
hynet/utilities/graph.py
hynet/utilities/rank1approx.py
hynet/visual/__init__.py
hynet/visual/graph.py
hynet/visual/opf.py
hynet/visual/capability/__init__.py
hynet/visual/capability/settings.py
hynet/visual/capability/utilities.py
hynet/visual/capability/visualizer.py
hynet-1.0.1.dist-info/DESCRIPTION.rst
hynet-1.0.1.dist-info/METADATA
hynet-1.0.1.dist-info/RECORD
hynet-1.0.1.dist-info/WHEEL
hynet-1.0.1.dist-info/metadata.json
hynet-1.0.1.dist-info/top_level.txt
