Metadata-Version: 2.0
Name: hynet
Version: 1.0.1
Summary: An optimal power flow framework for hybrid AC/DC power systems.
Home-page: http://www.msv.ei.tum.de/
Author: Matthias Hotz
Author-email: matthias.hotz@tum.de
License: BSD 3-clause license
Keywords: hybrid AC/DC power systems optimal power flow convex relaxation
Platform: UNKNOWN
Classifier: Development Status :: 5 - Production/Stable
Classifier: Topic :: Scientific/Engineering
Classifier: Intended Audience :: Science/Research
Classifier: Programming Language :: Python :: 3 :: Only
Classifier: License :: OSI Approved :: BSD License
Requires-Python: >=3.5
Provides-Extra: test
Provides-Extra: doc
Provides-Extra: graph
Requires-Dist: sqlalchemy (>=1.2.3)
Requires-Dist: numpy (>=1.14.0)
Requires-Dist: scipy (>=1.0.0)
Requires-Dist: pandas (>=0.23.0)
Requires-Dist: matplotlib (>=2.1.1)
Requires-Dist: h5py (>=2.8.0)
Provides-Extra: doc
Requires-Dist: Sphinx (>=1.7.8); extra == 'doc'
Requires-Dist: sphinxcontrib-napoleon (>=0.6.1); extra == 'doc'
Requires-Dist: numpydoc (>=0.8.0); extra == 'doc'
Requires-Dist: m2r (>=0.1.14); extra == 'doc'
Provides-Extra: graph
Requires-Dist: networkx (>=2.1); extra == 'graph'
Provides-Extra: test
Requires-Dist: pytest (>=3.5.0); extra == 'test'
Requires-Dist: pytest-cov; extra == 'test'
Requires-Dist: pylint (>=1.8.4); extra == 'test'
Requires-Dist: pylint-exit; extra == 'test'
Requires-Dist: PICOS (>=1.1.2); extra == 'test'
Requires-Dist: cvxopt (>=1.2.1); extra == 'test'
